{
  "base": "#151719",
  "surface0": "#1b2224",
  "surface1": "#1f3137",
  "overlay0": "#2c4a55",
  "text": "#b0c4c8",
  "subtext": "#638a90",
  "mauve": "#70e0c8",
  "blue": "#00b4b4",
  "teal": "#22c4a0",
  "green": "#50a870",
  "red": "#d05050",
  "yellow": "#c8a020",
  "pink": "#4ab8b8",
  "tab_active_fg": "#151719",
  "tab_active_bg": "#00b4b4",
  "tab_inactive_fg": "#638a90",
  "tab_inactive_bg": "#1b2224",
  "cursor_fg": "#151719",
  "cursor_bg": "#00b4b4",
  "selected_fg": "#70e0c8",
  "selected_bg": "#1f3137",
  "border_fg": "#1f3137",
  "panel_bg": "#151719",
  "title_fg": "#70e0c8",
  "color_dir": "#00b4b4",
  "color_symlink": "#4ab8b8",
  "color_image": "#70e0c8",
  "color_video": "#22c4a0",
  "color_audio": "#4ab8b8",
  "color_archive": "#c8a020",
  "color_doc": "#638a90",
  "color_code": "#50a870",
  "color_exec": "#22c4a0",
  "color_other": "#b0c4c8",
  "status_path_fg": "#151719",
  "status_path_bg": "#1f3137",
  "status_msg_fg": "#151719",
  "status_msg_bg": "#22c4a0",
  "status_err_fg": "#151719",
  "status_err_bg": "#d05050",
  "status_yank_fg": "#151719",
  "status_yank_bg": "#c8a020",
  "status_sel_fg": "#151719",
  "status_sel_bg": "#00b4b4",
  "status_hint_fg": "#70e0c8",
  "status_bar_fg": "#638a90",
  "status_bar_bg": "#1b2224",
  "popup_border_fg": "#00b4b4",
  "popup_bg": "#1b2224",
  "popup_text_fg": "#b0c4c8",
  "popup_dim_fg": "#2c4a55",
  "progress_filled_fg": "#00b4b4",
  "progress_empty_fg": "#1f3137",
  "settings_key_fg": "#70e0c8",
  "settings_val_fg": "#b0c4c8",
  "settings_cursor_fg": "#151719",
  "settings_cursor_bg": "#00b4b4",
  "warn_fg": "#151719",
  "warn_bg": "#c8a020"
}